setup.py
onyxmanager/Agent.py
onyxmanager/__init__.py
onyxmanager/json_sandbox.py
onyxmanager/test_case.py
onyxmanager.egg-info/PKG-INFO
onyxmanager.egg-info/SOURCES.txt
onyxmanager.egg-info/dependency_links.txt
onyxmanager.egg-info/not-zip-safe
onyxmanager.egg-info/top_level.txt