Metadata-Version: 1.0
Name: onyxmanager
Version: 0.0.5
Summary: OnyxManager device fact collector and setting/module manager.
Home-page: http://github.com/OnyxChills/onyxmanager
Author: Brandon Turmel
Author-email: brandonturmel@gmail.com
License: GNU
Platform: UNKNOWN
